{"name":"Search and verify results on ebay wesite for a non-registered user.","id":"stories/SearchResults.story;Search and verify results on ebay wesite for a non-registered user.","testSteps":[{"number":1,"description":"Example #1: {itemName\u003dshirt, 001\u003d}","duration":47635,"startTime":"2019-12-15T13:26:42.560Z[Europe/London]","precondition":false,"level":0,"children":[{"number":2,"description":"!-- This scenario can be reused for another items as well\nMeta:\n@001","duration":6,"startTime":"2019-12-15T13:26:42.566Z[Europe/London]","result":"IGNORED","precondition":false,"level":1},{"number":3,"description":"Given I am a non-registered customer","duration":5929,"startTime":"2019-12-15T13:26:42.580Z[Europe/London]","screenshots":[{"screenshot":"8b6ea68ab1c88a9123c9c6da0661b3bc2aea07cb787bedb0514de9598e4714f9.png","timeStamp":1576416408509}],"result":"SUCCESS","precondition":false,"level":1,"children":[{"number":4,"description":"Step Opened ebay website","duration":1219,"startTime":"2019-12-15T13:26:47.283Z[Europe/London]","screenshots":[{"screenshot":"8b6ea68ab1c88a9123c9c6da0661b3bc2aea07cb787bedb0514de9598e4714f9.png","timeStamp":1576416408497},{"screenshot":"8b6ea68ab1c88a9123c9c6da0661b3bc2aea07cb787bedb0514de9598e4714f9.png","timeStamp":1576416408502}],"result":"SUCCESS","precondition":false,"level":2}]},{"number":5,"description":"And I navigate to www.ebay.co.uk","duration":1673,"startTime":"2019-12-15T13:26:48.510Z[Europe/London]","screenshots":[{"screenshot":"8b6ea68ab1c88a9123c9c6da0661b3bc2aea07cb787bedb0514de9598e4714f9.png","timeStamp":1576416408511},{"screenshot":"9b634cc35452864e37d7c63e0009ab972f479d8dc8b4e9ea6ac1383bb4768a25.png","timeStamp":1576416410183}],"result":"SUCCESS","precondition":false,"level":1},{"number":6,"description":"When I search for an item {shirt}","duration":6442,"startTime":"2019-12-15T13:26:50.183Z[Europe/London]","screenshots":[{"screenshot":"9b634cc35452864e37d7c63e0009ab972f479d8dc8b4e9ea6ac1383bb4768a25.png","timeStamp":1576416410186},{"screenshot":"74d608d79acf07f89983d93757404bf497b54632e27a91de721c702b435c53c1.png","timeStamp":1576416416625}],"result":"SUCCESS","precondition":false,"level":1},{"number":7,"description":"Then I get a list of matching results","duration":1243,"startTime":"2019-12-15T13:26:56.626Z[Europe/London]","screenshots":[{"screenshot":"74d608d79acf07f89983d93757404bf497b54632e27a91de721c702b435c53c1.png","timeStamp":1576416416628},{"screenshot":"7ffe3e686904be3a8f1eed66b00577d7c09b3555e9e0a1cca04ee0ed1d0639cb.png","timeStamp":1576416417869}],"result":"SUCCESS","precondition":false,"level":1},{"number":8,"description":"And the resulting items cards show: postage price, No of bids, price or show BuyItNow tag","duration":2724,"startTime":"2019-12-15T13:26:57.870Z[Europe/London]","screenshots":[{"screenshot":"7ffe3e686904be3a8f1eed66b00577d7c09b3555e9e0a1cca04ee0ed1d0639cb.png","timeStamp":1576416417871},{"screenshot":"7ffe3e686904be3a8f1eed66b00577d7c09b3555e9e0a1cca04ee0ed1d0639cb.png","timeStamp":1576416420594}],"result":"SUCCESS","precondition":false,"level":1},{"number":9,"description":"Then I can sort the results by {Lowest Price}","duration":9095,"startTime":"2019-12-15T13:27:00.595Z[Europe/London]","screenshots":[{"screenshot":"7ffe3e686904be3a8f1eed66b00577d7c09b3555e9e0a1cca04ee0ed1d0639cb.png","timeStamp":1576416420596},{"screenshot":"e9a47e239f81cf0b3fe132cc2f188c47ad7d0eeafa4bea4819d26fd0dea10b3a.png","timeStamp":1576416429690}],"result":"SUCCESS","precondition":false,"level":1,"children":[{"number":10,"description":"Step Selected sort value Lowest Price","duration":6,"startTime":"2019-12-15T13:27:00.601Z[Europe/London]","screenshots":[{"screenshot":"7ffe3e686904be3a8f1eed66b00577d7c09b3555e9e0a1cca04ee0ed1d0639cb.png","timeStamp":1576416420604},{"screenshot":"7ffe3e686904be3a8f1eed66b00577d7c09b3555e9e0a1cca04ee0ed1d0639cb.png","timeStamp":1576416420606}],"result":"SUCCESS","precondition":false,"level":2}]},{"number":11,"description":"And the results are listed in the page in the correct order","duration":4641,"startTime":"2019-12-15T13:27:09.691Z[Europe/London]","screenshots":[{"screenshot":"e9a47e239f81cf0b3fe132cc2f188c47ad7d0eeafa4bea4819d26fd0dea10b3a.png","timeStamp":1576416429692},{"screenshot":"e9a47e239f81cf0b3fe132cc2f188c47ad7d0eeafa4bea4819d26fd0dea10b3a.png","timeStamp":1576416434332}],"result":"SUCCESS","precondition":false,"level":1,"children":[{"number":12,"description":"Step Verifying the sort order","duration":5,"startTime":"2019-12-15T13:27:09.694Z[Europe/London]","screenshots":[{"screenshot":"e9a47e239f81cf0b3fe132cc2f188c47ad7d0eeafa4bea4819d26fd0dea10b3a.png","timeStamp":1576416429697},{"screenshot":"e9a47e239f81cf0b3fe132cc2f188c47ad7d0eeafa4bea4819d26fd0dea10b3a.png","timeStamp":1576416429699}],"result":"SUCCESS","precondition":false,"level":2},{"number":13,"description":"Step Verified the sort order and its correct","duration":503,"startTime":"2019-12-15T13:27:13.828Z[Europe/London]","screenshots":[{"screenshot":"e9a47e239f81cf0b3fe132cc2f188c47ad7d0eeafa4bea4819d26fd0dea10b3a.png","timeStamp":1576416434328},{"screenshot":"e9a47e239f81cf0b3fe132cc2f188c47ad7d0eeafa4bea4819d26fd0dea10b3a.png","timeStamp":1576416434331}],"result":"SUCCESS","precondition":false,"level":2}]},{"number":14,"description":"Then I can sort the results by {Highest Price}","duration":7333,"startTime":"2019-12-15T13:27:14.333Z[Europe/London]","screenshots":[{"screenshot":"e9a47e239f81cf0b3fe132cc2f188c47ad7d0eeafa4bea4819d26fd0dea10b3a.png","timeStamp":1576416434334},{"screenshot":"7393e04ed75ce0b4de776fefb20519088e9e3733a1c315f764661ed9b8790e75.png","timeStamp":1576416441666}],"result":"SUCCESS","precondition":false,"level":1,"children":[{"number":15,"description":"Step Selected sort value Highest Price","duration":12,"startTime":"2019-12-15T13:27:14.336Z[Europe/London]","screenshots":[{"screenshot":"e9a47e239f81cf0b3fe132cc2f188c47ad7d0eeafa4bea4819d26fd0dea10b3a.png","timeStamp":1576416434345},{"screenshot":"e9a47e239f81cf0b3fe132cc2f188c47ad7d0eeafa4bea4819d26fd0dea10b3a.png","timeStamp":1576416434348}],"result":"SUCCESS","precondition":false,"level":2}]},{"number":16,"description":"And the results are listed in the page in the correct order","duration":4739,"startTime":"2019-12-15T13:27:21.666Z[Europe/London]","screenshots":[{"screenshot":"7393e04ed75ce0b4de776fefb20519088e9e3733a1c315f764661ed9b8790e75.png","timeStamp":1576416441667},{"screenshot":"7393e04ed75ce0b4de776fefb20519088e9e3733a1c315f764661ed9b8790e75.png","timeStamp":1576416446405}],"result":"SUCCESS","precondition":false,"level":1,"children":[{"number":17,"description":"Step Verifying the sort order","duration":3,"startTime":"2019-12-15T13:27:21.669Z[Europe/London]","screenshots":[{"screenshot":"7393e04ed75ce0b4de776fefb20519088e9e3733a1c315f764661ed9b8790e75.png","timeStamp":1576416441671},{"screenshot":"7393e04ed75ce0b4de776fefb20519088e9e3733a1c315f764661ed9b8790e75.png","timeStamp":1576416441672}],"result":"SUCCESS","precondition":false,"level":2},{"number":18,"description":"Step Verified the sort order and its correct","duration":512,"startTime":"2019-12-15T13:27:25.892Z[Europe/London]","screenshots":[{"screenshot":"7393e04ed75ce0b4de776fefb20519088e9e3733a1c315f764661ed9b8790e75.png","timeStamp":1576416446403},{"screenshot":"7393e04ed75ce0b4de776fefb20519088e9e3733a1c315f764661ed9b8790e75.png","timeStamp":1576416446404}],"result":"SUCCESS","precondition":false,"level":2}]},{"number":19,"description":"Then I can filter the results by {Buy it now}","duration":3747,"startTime":"2019-12-15T13:27:26.405Z[Europe/London]","screenshots":[{"screenshot":"7393e04ed75ce0b4de776fefb20519088e9e3733a1c315f764661ed9b8790e75.png","timeStamp":1576416446406},{"screenshot":"64851f76c6a02998ec772324df97215506e0ee12160b5a5af8405f7337693272.png","timeStamp":1576416450151}],"result":"SUCCESS","precondition":false,"level":1},{"number":20,"description":"And all the results shown in the page have the {Buy it now} tag","duration":40,"startTime":"2019-12-15T13:27:30.154Z[Europe/London]","screenshots":[{"screenshot":"64851f76c6a02998ec772324df97215506e0ee12160b5a5af8405f7337693272.png","timeStamp":1576416450154},{"screenshot":"64851f76c6a02998ec772324df97215506e0ee12160b5a5af8405f7337693272.png","timeStamp":1576416450194}],"result":"SUCCESS","precondition":false,"level":1,"children":[{"number":21,"description":"Step Verified Buy it now on UI","duration":2,"startTime":"2019-12-15T13:27:30.191Z[Europe/London]","screenshots":[{"screenshot":"64851f76c6a02998ec772324df97215506e0ee12160b5a5af8405f7337693272.png","timeStamp":1576416450192},{"screenshot":"64851f76c6a02998ec772324df97215506e0ee12160b5a5af8405f7337693272.png","timeStamp":1576416450193}],"result":"SUCCESS","precondition":false,"level":2}]}]}],"userStory":{"id":"SearchResults","storyName":"Search results","path":"SearchResults.story","narrative":"As a user\nI want to perform an action\nSo that I can achieve a business goal","type":"story"},"featureTag":{"name":"Search results","type":"story","displayName":"Search results"},"title":"Search and verify results on ebay wesite for a non-registered user.","tags":[{"name":"Search Results","type":"story","displayName":"Search Results"}],"startTime":"2019-12-15T13:26:42.438Z[Europe/London]","duration":47871,"projectKey":"","dataTable":{"headers":["itemName"],"rows":[{"values":["shirt"],"result":"SUCCESS"}],"predefinedRows":true,"scenarioOutline":"!-- This scenario can be reused for another items as well\nMeta:\n@001\nGiven I am a non-registered customer\nAnd I navigate to www.ebay.co.uk\nWhen I search for an item \u003citemName\u003e\nThen I get a list of matching results\nAnd the resulting items cards show: postage price, No of bids, price or show BuyItNow tag\nThen I can sort the results by Lowest Price\nAnd the results are listed in the page in the correct order\nThen I can sort the results by Highest Price\nAnd the results are listed in the page in the correct order\nThen I can filter the results by Buy it now\nAnd all the results shown in the page have the Buy it now tag\n","dataSetDescriptors":[{"startRow":0,"rowCount":0}]},"manual":false,"testSource":"JBehave","result":"SUCCESS"}